<mxfile modified="2019-12-09T07:56:37.816Z" host="www.draw.io" agent="Mozilla/5.0 (Macintosh; Intel Mac OS X 10.15; rv:71.0) Gecko/20100101 Firefox/71.0" etag="5xU_JzAIChipr5toqX3a" version="12.3.8" type="github" pages="1">
  <diagram id="PPIrIhba18o_3io6QQd2" name="Page-1">
    <mxGraphModel dx="2489" dy="888" grid="1" gridSize="10" guides="1" tooltips="1" connect="1" arrows="1" fold="1" page="1" pageScale="1" pageWidth="850" pageHeight="1100" math="0" shadow="0">
      <root>
        <mxCell id="0"/>
        <mxCell id="1" parent="0"/>
        <mxCell id="wNCc4e_4xXsxz9gpfNG5-50" style="edgeStyle=orthogonalEdgeStyle;rounded=0;html=1;exitX=0.5;exitY=1;jettySize=auto;orthogonalLoop=1;fontSize=18;" parent="1" source="wNCc4e_4xXsxz9gpfNG5-1" target="wNCc4e_4xXsxz9gpfNG5-6" edge="1">
          <mxGeometry relative="1" as="geometry"/>
        </mxCell>
        <mxCell id="wNCc4e_4xXsxz9gpfNG5-51" style="edgeStyle=orthogonalEdgeStyle;rounded=0;html=1;exitX=0.5;exitY=1;jettySize=auto;orthogonalLoop=1;fontSize=18;" parent="1" source="wNCc4e_4xXsxz9gpfNG5-1" target="wNCc4e_4xXsxz9gpfNG5-7" edge="1">
          <mxGeometry relative="1" as="geometry"/>
        </mxCell>
        <mxCell id="wNCc4e_4xXsxz9gpfNG5-52" style="edgeStyle=orthogonalEdgeStyle;rounded=0;html=1;exitX=0.5;exitY=1;jettySize=auto;orthogonalLoop=1;fontSize=18;" parent="1" source="wNCc4e_4xXsxz9gpfNG5-1" target="wNCc4e_4xXsxz9gpfNG5-29" edge="1">
          <mxGeometry relative="1" as="geometry"/>
        </mxCell>
        <mxCell id="wNCc4e_4xXsxz9gpfNG5-55" style="edgeStyle=orthogonalEdgeStyle;rounded=0;html=1;exitX=0.5;exitY=1;entryX=0.5;entryY=0;jettySize=auto;orthogonalLoop=1;fontSize=18;" parent="1" source="wNCc4e_4xXsxz9gpfNG5-1" target="wNCc4e_4xXsxz9gpfNG5-36" edge="1">
          <mxGeometry relative="1" as="geometry"/>
        </mxCell>
        <mxCell id="wNCc4e_4xXsxz9gpfNG5-56" style="edgeStyle=orthogonalEdgeStyle;rounded=0;html=1;exitX=0.5;exitY=1;jettySize=auto;orthogonalLoop=1;fontSize=18;" parent="1" source="wNCc4e_4xXsxz9gpfNG5-1" target="wNCc4e_4xXsxz9gpfNG5-37" edge="1">
          <mxGeometry relative="1" as="geometry"/>
        </mxCell>
        <mxCell id="wNCc4e_4xXsxz9gpfNG5-57" style="edgeStyle=orthogonalEdgeStyle;rounded=0;html=1;exitX=0.5;exitY=1;entryX=0.5;entryY=0;jettySize=auto;orthogonalLoop=1;fontSize=18;" parent="1" source="wNCc4e_4xXsxz9gpfNG5-1" target="wNCc4e_4xXsxz9gpfNG5-38" edge="1">
          <mxGeometry relative="1" as="geometry"/>
        </mxCell>
        <mxCell id="wNCc4e_4xXsxz9gpfNG5-58" style="edgeStyle=orthogonalEdgeStyle;rounded=0;html=1;exitX=0.5;exitY=1;entryX=0.5;entryY=0;jettySize=auto;orthogonalLoop=1;fontSize=18;" parent="1" source="wNCc4e_4xXsxz9gpfNG5-1" target="wNCc4e_4xXsxz9gpfNG5-44" edge="1">
          <mxGeometry relative="1" as="geometry"/>
        </mxCell>
        <mxCell id="p3O5Rhy82yDMZXPunIYx-20" style="edgeStyle=orthogonalEdgeStyle;rounded=0;html=1;exitX=0.5;exitY=1;jettySize=auto;orthogonalLoop=1;" parent="1" source="wNCc4e_4xXsxz9gpfNG5-1" target="p3O5Rhy82yDMZXPunIYx-15" edge="1">
          <mxGeometry relative="1" as="geometry">
            <Array as="points">
              <mxPoint x="571" y="260"/>
              <mxPoint x="50" y="260"/>
            </Array>
          </mxGeometry>
        </mxCell>
        <mxCell id="wNCc4e_4xXsxz9gpfNG5-1" value="Permsin Steel Works" style="rounded=1;whiteSpace=wrap;html=1;fontSize=18;" parent="1" vertex="1">
          <mxGeometry x="438" y="100" width="265" height="110" as="geometry"/>
        </mxCell>
        <mxCell id="wNCc4e_4xXsxz9gpfNG5-6" value="Home" style="rounded=1;whiteSpace=wrap;html=1;" parent="1" vertex="1">
          <mxGeometry x="-380" y="310" width="120" height="60" as="geometry"/>
        </mxCell>
        <mxCell id="wNCc4e_4xXsxz9gpfNG5-22" style="edgeStyle=orthogonalEdgeStyle;rounded=0;html=1;exitX=0.5;exitY=1;entryX=0;entryY=0.5;jettySize=auto;orthogonalLoop=1;fontSize=8;" parent="1" source="wNCc4e_4xXsxz9gpfNG5-7" target="wNCc4e_4xXsxz9gpfNG5-13" edge="1">
          <mxGeometry relative="1" as="geometry"/>
        </mxCell>
        <mxCell id="wNCc4e_4xXsxz9gpfNG5-23" style="edgeStyle=orthogonalEdgeStyle;rounded=0;html=1;exitX=0.5;exitY=1;entryX=0;entryY=0.5;jettySize=auto;orthogonalLoop=1;fontSize=8;" parent="1" source="wNCc4e_4xXsxz9gpfNG5-7" target="wNCc4e_4xXsxz9gpfNG5-15" edge="1">
          <mxGeometry relative="1" as="geometry"/>
        </mxCell>
        <mxCell id="gMr6Nnkb4Np37UVj3Ji1-5" style="edgeStyle=orthogonalEdgeStyle;rounded=0;html=1;exitX=0.5;exitY=1;entryX=0;entryY=0.5;jettySize=auto;orthogonalLoop=1;" parent="1" source="wNCc4e_4xXsxz9gpfNG5-7" target="gMr6Nnkb4Np37UVj3Ji1-4" edge="1">
          <mxGeometry relative="1" as="geometry"/>
        </mxCell>
        <mxCell id="EYkipQbO91oZOMfpL7uJ-2" style="edgeStyle=orthogonalEdgeStyle;rounded=0;html=1;exitX=0.5;exitY=1;entryX=0;entryY=0.5;jettySize=auto;orthogonalLoop=1;" parent="1" source="wNCc4e_4xXsxz9gpfNG5-7" target="wNCc4e_4xXsxz9gpfNG5-19" edge="1">
          <mxGeometry relative="1" as="geometry"/>
        </mxCell>
        <mxCell id="Dp0uku5MoqhAA5mbejGY-7" style="edgeStyle=orthogonalEdgeStyle;rounded=0;orthogonalLoop=1;jettySize=auto;html=1;exitX=0.5;exitY=1;exitDx=0;exitDy=0;entryX=0;entryY=0.5;entryDx=0;entryDy=0;" parent="1" source="wNCc4e_4xXsxz9gpfNG5-7" target="Dp0uku5MoqhAA5mbejGY-6" edge="1">
          <mxGeometry relative="1" as="geometry"/>
        </mxCell>
        <mxCell id="wNCc4e_4xXsxz9gpfNG5-7" value="Company" style="rounded=1;whiteSpace=wrap;html=1;" parent="1" vertex="1">
          <mxGeometry x="-200" y="310" width="120" height="60" as="geometry"/>
        </mxCell>
        <mxCell id="wNCc4e_4xXsxz9gpfNG5-13" value="Company History&lt;br&gt;" style="rounded=1;whiteSpace=wrap;html=1;fontSize=8;" parent="1" vertex="1">
          <mxGeometry x="-114" y="409.5" width="70" height="30" as="geometry"/>
        </mxCell>
        <mxCell id="wNCc4e_4xXsxz9gpfNG5-15" value="Our Board" style="rounded=1;whiteSpace=wrap;html=1;fontSize=8;" parent="1" vertex="1">
          <mxGeometry x="-115" y="491.5" width="70" height="30" as="geometry"/>
        </mxCell>
        <mxCell id="wNCc4e_4xXsxz9gpfNG5-19" value="Our Business" style="rounded=1;whiteSpace=wrap;html=1;fontSize=8;" parent="1" vertex="1">
          <mxGeometry x="-115" y="451" width="70" height="30" as="geometry"/>
        </mxCell>
        <mxCell id="1SbDq5obIm_g6BfvqbwU-26" style="edgeStyle=orthogonalEdgeStyle;rounded=0;html=1;exitX=0.5;exitY=1;entryX=0;entryY=0.5;jettySize=auto;orthogonalLoop=1;" parent="1" source="wNCc4e_4xXsxz9gpfNG5-29" target="p3O5Rhy82yDMZXPunIYx-30" edge="1">
          <mxGeometry relative="1" as="geometry"/>
        </mxCell>
        <mxCell id="1SbDq5obIm_g6BfvqbwU-27" style="edgeStyle=orthogonalEdgeStyle;rounded=0;html=1;exitX=0.5;exitY=1;entryX=0;entryY=0.5;jettySize=auto;orthogonalLoop=1;" parent="1" source="wNCc4e_4xXsxz9gpfNG5-29" target="p3O5Rhy82yDMZXPunIYx-31" edge="1">
          <mxGeometry relative="1" as="geometry"/>
        </mxCell>
        <mxCell id="1SbDq5obIm_g6BfvqbwU-28" style="edgeStyle=orthogonalEdgeStyle;rounded=0;html=1;exitX=0.5;exitY=1;entryX=0;entryY=0.5;jettySize=auto;orthogonalLoop=1;" parent="1" source="wNCc4e_4xXsxz9gpfNG5-29" target="p3O5Rhy82yDMZXPunIYx-32" edge="1">
          <mxGeometry relative="1" as="geometry"/>
        </mxCell>
        <mxCell id="I7oUZK_1feLerxIwC8QW-1" style="edgeStyle=orthogonalEdgeStyle;rounded=0;orthogonalLoop=1;jettySize=auto;html=1;exitX=0.25;exitY=1;exitDx=0;exitDy=0;entryX=0.25;entryY=0;entryDx=0;entryDy=0;" edge="1" parent="1" source="wNCc4e_4xXsxz9gpfNG5-29" target="wNCc4e_4xXsxz9gpfNG5-34">
          <mxGeometry relative="1" as="geometry"/>
        </mxCell>
        <mxCell id="wNCc4e_4xXsxz9gpfNG5-29" value="Products and Services" style="rounded=1;whiteSpace=wrap;html=1;" parent="1" vertex="1">
          <mxGeometry x="170" y="310" width="120" height="60" as="geometry"/>
        </mxCell>
        <mxCell id="p3O5Rhy82yDMZXPunIYx-43" style="edgeStyle=orthogonalEdgeStyle;rounded=0;html=1;exitX=0.5;exitY=1;entryX=0;entryY=0.5;jettySize=auto;orthogonalLoop=1;" parent="1" source="wNCc4e_4xXsxz9gpfNG5-34" target="p3O5Rhy82yDMZXPunIYx-42" edge="1">
          <mxGeometry relative="1" as="geometry"/>
        </mxCell>
        <mxCell id="p3O5Rhy82yDMZXPunIYx-47" style="edgeStyle=orthogonalEdgeStyle;rounded=0;html=1;exitX=0.5;exitY=1;entryX=0;entryY=0.5;jettySize=auto;orthogonalLoop=1;" parent="1" source="wNCc4e_4xXsxz9gpfNG5-34" target="p3O5Rhy82yDMZXPunIYx-44" edge="1">
          <mxGeometry relative="1" as="geometry"/>
        </mxCell>
        <mxCell id="p3O5Rhy82yDMZXPunIYx-48" style="edgeStyle=orthogonalEdgeStyle;rounded=0;html=1;exitX=0.5;exitY=1;entryX=0;entryY=0.5;jettySize=auto;orthogonalLoop=1;" parent="1" source="wNCc4e_4xXsxz9gpfNG5-34" target="p3O5Rhy82yDMZXPunIYx-45" edge="1">
          <mxGeometry relative="1" as="geometry"/>
        </mxCell>
        <mxCell id="p3O5Rhy82yDMZXPunIYx-49" style="edgeStyle=orthogonalEdgeStyle;rounded=0;html=1;exitX=0.5;exitY=1;entryX=0;entryY=0.5;jettySize=auto;orthogonalLoop=1;" parent="1" source="wNCc4e_4xXsxz9gpfNG5-34" target="p3O5Rhy82yDMZXPunIYx-46" edge="1">
          <mxGeometry relative="1" as="geometry"/>
        </mxCell>
        <mxCell id="wNCc4e_4xXsxz9gpfNG5-34" value="Services" style="rounded=1;whiteSpace=wrap;html=1;" parent="1" vertex="1">
          <mxGeometry x="170" y="540" width="120" height="60" as="geometry"/>
        </mxCell>
        <mxCell id="wNCc4e_4xXsxz9gpfNG5-36" value="News and Activities" style="rounded=1;whiteSpace=wrap;html=1;" parent="1" vertex="1">
          <mxGeometry x="610" y="310" width="120" height="60" as="geometry"/>
        </mxCell>
        <mxCell id="wNCc4e_4xXsxz9gpfNG5-37" value="Investors&amp;nbsp;(IRPLUS)" style="rounded=1;whiteSpace=wrap;html=1;" parent="1" vertex="1">
          <mxGeometry x="780" y="310" width="120" height="60" as="geometry"/>
        </mxCell>
        <mxCell id="wNCc4e_4xXsxz9gpfNG5-38" value="Download" style="rounded=1;whiteSpace=wrap;html=1;" parent="1" vertex="1">
          <mxGeometry x="940" y="310" width="120" height="60" as="geometry"/>
        </mxCell>
        <mxCell id="wNCc4e_4xXsxz9gpfNG5-43" style="edgeStyle=orthogonalEdgeStyle;rounded=0;html=1;exitX=0.5;exitY=1;entryX=0;entryY=0.5;jettySize=auto;orthogonalLoop=1;fontSize=8;" parent="1" source="wNCc4e_4xXsxz9gpfNG5-44" target="wNCc4e_4xXsxz9gpfNG5-45" edge="1">
          <mxGeometry relative="1" as="geometry"/>
        </mxCell>
        <mxCell id="wNCc4e_4xXsxz9gpfNG5-47" style="edgeStyle=orthogonalEdgeStyle;rounded=0;html=1;exitX=0.5;exitY=1;entryX=0;entryY=0.5;jettySize=auto;orthogonalLoop=1;fontSize=8;" parent="1" source="wNCc4e_4xXsxz9gpfNG5-44" target="wNCc4e_4xXsxz9gpfNG5-46" edge="1">
          <mxGeometry relative="1" as="geometry"/>
        </mxCell>
        <mxCell id="wNCc4e_4xXsxz9gpfNG5-49" style="edgeStyle=orthogonalEdgeStyle;rounded=0;html=1;exitX=0.5;exitY=1;entryX=0;entryY=0.5;jettySize=auto;orthogonalLoop=1;fontSize=8;" parent="1" source="wNCc4e_4xXsxz9gpfNG5-44" target="wNCc4e_4xXsxz9gpfNG5-48" edge="1">
          <mxGeometry relative="1" as="geometry"/>
        </mxCell>
        <mxCell id="wNCc4e_4xXsxz9gpfNG5-44" value="Contact and Support" style="rounded=1;whiteSpace=wrap;html=1;" parent="1" vertex="1">
          <mxGeometry x="1110" y="310" width="120" height="60" as="geometry"/>
        </mxCell>
        <mxCell id="wNCc4e_4xXsxz9gpfNG5-45" value="Contact Us" style="rounded=1;whiteSpace=wrap;html=1;fontSize=8;" parent="1" vertex="1">
          <mxGeometry x="1205" y="410" width="70" height="30" as="geometry"/>
        </mxCell>
        <mxCell id="wNCc4e_4xXsxz9gpfNG5-46" value="Career (external site)" style="rounded=1;whiteSpace=wrap;html=1;fontSize=8;" parent="1" vertex="1">
          <mxGeometry x="1205" y="450" width="70" height="30" as="geometry"/>
        </mxCell>
        <mxCell id="wNCc4e_4xXsxz9gpfNG5-48" value="Knowledge bases (external site)" style="rounded=1;whiteSpace=wrap;html=1;fontSize=8;" parent="1" vertex="1">
          <mxGeometry x="1205" y="490" width="70" height="30" as="geometry"/>
        </mxCell>
        <mxCell id="p3O5Rhy82yDMZXPunIYx-26" style="edgeStyle=orthogonalEdgeStyle;rounded=0;html=1;exitX=0.5;exitY=1;entryX=0;entryY=0.5;jettySize=auto;orthogonalLoop=1;" parent="1" source="p3O5Rhy82yDMZXPunIYx-15" target="p3O5Rhy82yDMZXPunIYx-22" edge="1">
          <mxGeometry relative="1" as="geometry"/>
        </mxCell>
        <mxCell id="EYkipQbO91oZOMfpL7uJ-1" style="edgeStyle=orthogonalEdgeStyle;rounded=0;html=1;exitX=0.5;exitY=1;entryX=0;entryY=0.5;jettySize=auto;orthogonalLoop=1;" parent="1" source="p3O5Rhy82yDMZXPunIYx-15" target="yPXZ2-zauQyehbcSFZ-F-1" edge="1">
          <mxGeometry relative="1" as="geometry"/>
        </mxCell>
        <mxCell id="Dp0uku5MoqhAA5mbejGY-4" style="edgeStyle=orthogonalEdgeStyle;rounded=0;orthogonalLoop=1;jettySize=auto;html=1;exitX=0.5;exitY=1;exitDx=0;exitDy=0;entryX=0;entryY=0.5;entryDx=0;entryDy=0;" parent="1" source="p3O5Rhy82yDMZXPunIYx-15" target="Dp0uku5MoqhAA5mbejGY-3" edge="1">
          <mxGeometry relative="1" as="geometry"/>
        </mxCell>
        <mxCell id="Dp0uku5MoqhAA5mbejGY-11" style="edgeStyle=orthogonalEdgeStyle;rounded=0;orthogonalLoop=1;jettySize=auto;html=1;exitX=0.5;exitY=1;exitDx=0;exitDy=0;entryX=0;entryY=0.5;entryDx=0;entryDy=0;" parent="1" source="p3O5Rhy82yDMZXPunIYx-15" target="Dp0uku5MoqhAA5mbejGY-10" edge="1">
          <mxGeometry relative="1" as="geometry"/>
        </mxCell>
        <mxCell id="p3O5Rhy82yDMZXPunIYx-15" value="Our Values" style="rounded=1;whiteSpace=wrap;html=1;" parent="1" vertex="1">
          <mxGeometry x="-10" y="310" width="120" height="60" as="geometry"/>
        </mxCell>
        <mxCell id="p3O5Rhy82yDMZXPunIYx-22" value="Mission, Vision &amp;amp; Objective" style="rounded=1;whiteSpace=wrap;html=1;fontSize=8;" parent="1" vertex="1">
          <mxGeometry x="70" y="410" width="70" height="30" as="geometry"/>
        </mxCell>
        <mxCell id="p3O5Rhy82yDMZXPunIYx-30" value="Cold rolled (CR)" style="rounded=1;whiteSpace=wrap;html=1;fontSize=8;" parent="1" vertex="1">
          <mxGeometry x="249.5" y="411" width="70" height="30" as="geometry"/>
        </mxCell>
        <mxCell id="p3O5Rhy82yDMZXPunIYx-31" value="Galvanized Iron (GI)" style="rounded=1;whiteSpace=wrap;html=1;fontSize=8;" parent="1" vertex="1">
          <mxGeometry x="249.5" y="451" width="70" height="30" as="geometry"/>
        </mxCell>
        <mxCell id="p3O5Rhy82yDMZXPunIYx-32" value="Hot rolled (HR)" style="rounded=1;whiteSpace=wrap;html=1;fontSize=8;" parent="1" vertex="1">
          <mxGeometry x="249.5" y="491" width="70" height="30" as="geometry"/>
        </mxCell>
        <mxCell id="p3O5Rhy82yDMZXPunIYx-33" value="Steel, Aluminum or Zinc (AZ)" style="rounded=1;whiteSpace=wrap;html=1;fontSize=8;" parent="1" vertex="1">
          <mxGeometry x="-320.5" y="735.5" width="70" height="30" as="geometry"/>
        </mxCell>
        <mxCell id="p3O5Rhy82yDMZXPunIYx-34" value="High Strength Purlin (CEE &amp;amp; ZED)" style="rounded=1;whiteSpace=wrap;html=1;fontSize=8;" parent="1" vertex="1">
          <mxGeometry x="-318.5" y="775.5" width="70" height="30" as="geometry"/>
        </mxCell>
        <mxCell id="p3O5Rhy82yDMZXPunIYx-35" value="Steel Coating (PP)" style="rounded=1;whiteSpace=wrap;html=1;fontSize=8;" parent="1" vertex="1">
          <mxGeometry x="-318.5" y="815.5" width="70" height="30" as="geometry"/>
        </mxCell>
        <mxCell id="p3O5Rhy82yDMZXPunIYx-42" value="Cutting&lt;br&gt;" style="rounded=1;whiteSpace=wrap;html=1;fontSize=8;" parent="1" vertex="1">
          <mxGeometry x="249.5" y="638.5" width="70" height="30" as="geometry"/>
        </mxCell>
        <mxCell id="p3O5Rhy82yDMZXPunIYx-44" value="Slitter Line" style="rounded=1;whiteSpace=wrap;html=1;fontSize=8;" parent="1" vertex="1">
          <mxGeometry x="249.5" y="678.5" width="70" height="30" as="geometry"/>
        </mxCell>
        <mxCell id="p3O5Rhy82yDMZXPunIYx-45" value="Packing" style="rounded=1;whiteSpace=wrap;html=1;fontSize=8;" parent="1" vertex="1">
          <mxGeometry x="249.5" y="719.5" width="70" height="30" as="geometry"/>
        </mxCell>
        <mxCell id="p3O5Rhy82yDMZXPunIYx-46" value="Delivery" style="rounded=1;whiteSpace=wrap;html=1;fontSize=8;" parent="1" vertex="1">
          <mxGeometry x="249.5" y="760.5" width="70" height="30" as="geometry"/>
        </mxCell>
        <mxCell id="gMr6Nnkb4Np37UVj3Ji1-4" value="Corporate Governance" style="rounded=1;whiteSpace=wrap;html=1;fontSize=8;" parent="1" vertex="1">
          <mxGeometry x="-115" y="570" width="70" height="30" as="geometry"/>
        </mxCell>
        <mxCell id="yPXZ2-zauQyehbcSFZ-F-1" value="Certification and Award" style="rounded=1;whiteSpace=wrap;html=1;fontSize=8;" parent="1" vertex="1">
          <mxGeometry x="72" y="540" width="70" height="30" as="geometry"/>
        </mxCell>
        <mxCell id="1SbDq5obIm_g6BfvqbwU-17" value="Metal Sheet&lt;br&gt;" style="rounded=1;whiteSpace=wrap;html=1;fontSize=8;" parent="1" vertex="1">
          <mxGeometry x="-324.5" y="535.5" width="70" height="30" as="geometry"/>
        </mxCell>
        <mxCell id="1SbDq5obIm_g6BfvqbwU-18" value="PU Roof&lt;br&gt;" style="rounded=1;whiteSpace=wrap;html=1;fontSize=8;" parent="1" vertex="1">
          <mxGeometry x="-322.5" y="575.5" width="70" height="30" as="geometry"/>
        </mxCell>
        <mxCell id="1SbDq5obIm_g6BfvqbwU-19" value="Panel&lt;br&gt;" style="rounded=1;whiteSpace=wrap;html=1;fontSize=8;" parent="1" vertex="1">
          <mxGeometry x="-321.5" y="615.5" width="70" height="30" as="geometry"/>
        </mxCell>
        <mxCell id="1SbDq5obIm_g6BfvqbwU-44" style="edgeStyle=orthogonalEdgeStyle;rounded=0;html=1;exitX=0.5;exitY=1;entryX=0;entryY=0.5;jettySize=auto;orthogonalLoop=1;" parent="1" source="1SbDq5obIm_g6BfvqbwU-20" target="1SbDq5obIm_g6BfvqbwU-17" edge="1">
          <mxGeometry relative="1" as="geometry"/>
        </mxCell>
        <mxCell id="1SbDq5obIm_g6BfvqbwU-45" style="edgeStyle=orthogonalEdgeStyle;rounded=0;html=1;exitX=0.5;exitY=1;entryX=0;entryY=0.25;jettySize=auto;orthogonalLoop=1;" parent="1" source="1SbDq5obIm_g6BfvqbwU-20" target="1SbDq5obIm_g6BfvqbwU-18" edge="1">
          <mxGeometry relative="1" as="geometry"/>
        </mxCell>
        <mxCell id="1SbDq5obIm_g6BfvqbwU-46" style="edgeStyle=orthogonalEdgeStyle;rounded=0;html=1;exitX=0.5;exitY=1;entryX=0;entryY=0.5;jettySize=auto;orthogonalLoop=1;" parent="1" source="1SbDq5obIm_g6BfvqbwU-20" target="1SbDq5obIm_g6BfvqbwU-19" edge="1">
          <mxGeometry relative="1" as="geometry"/>
        </mxCell>
        <mxCell id="1SbDq5obIm_g6BfvqbwU-47" style="edgeStyle=orthogonalEdgeStyle;rounded=0;html=1;exitX=0.5;exitY=1;entryX=0;entryY=0.5;jettySize=auto;orthogonalLoop=1;" parent="1" source="1SbDq5obIm_g6BfvqbwU-20" target="1SbDq5obIm_g6BfvqbwU-22" edge="1">
          <mxGeometry relative="1" as="geometry"/>
        </mxCell>
        <mxCell id="1SbDq5obIm_g6BfvqbwU-20" value="Metal Sheet and Panel" style="rounded=1;whiteSpace=wrap;html=1;fontSize=8;" parent="1" vertex="1">
          <mxGeometry x="-391.5" y="496.5" width="70" height="30" as="geometry"/>
        </mxCell>
        <mxCell id="1SbDq5obIm_g6BfvqbwU-36" style="edgeStyle=orthogonalEdgeStyle;rounded=0;html=1;exitX=0.5;exitY=1;entryX=0;entryY=0.5;jettySize=auto;orthogonalLoop=1;" parent="1" source="1SbDq5obIm_g6BfvqbwU-21" target="p3O5Rhy82yDMZXPunIYx-33" edge="1">
          <mxGeometry relative="1" as="geometry"/>
        </mxCell>
        <mxCell id="1SbDq5obIm_g6BfvqbwU-39" style="edgeStyle=orthogonalEdgeStyle;rounded=0;html=1;exitX=0.5;exitY=1;entryX=0;entryY=0.5;jettySize=auto;orthogonalLoop=1;" parent="1" source="1SbDq5obIm_g6BfvqbwU-21" target="p3O5Rhy82yDMZXPunIYx-34" edge="1">
          <mxGeometry relative="1" as="geometry"/>
        </mxCell>
        <mxCell id="1SbDq5obIm_g6BfvqbwU-40" style="edgeStyle=orthogonalEdgeStyle;rounded=0;html=1;exitX=0.5;exitY=1;entryX=0;entryY=0.5;jettySize=auto;orthogonalLoop=1;" parent="1" source="1SbDq5obIm_g6BfvqbwU-21" target="p3O5Rhy82yDMZXPunIYx-35" edge="1">
          <mxGeometry relative="1" as="geometry"/>
        </mxCell>
        <mxCell id="1SbDq5obIm_g6BfvqbwU-21" value="Steel Coil&lt;br&gt;" style="rounded=1;whiteSpace=wrap;html=1;fontSize=8;" parent="1" vertex="1">
          <mxGeometry x="-390.5" y="695" width="70" height="30" as="geometry"/>
        </mxCell>
        <mxCell id="1SbDq5obIm_g6BfvqbwU-22" value="Purlin&lt;br&gt;" style="rounded=1;whiteSpace=wrap;html=1;fontSize=8;" parent="1" vertex="1">
          <mxGeometry x="-321.5" y="655.5" width="70" height="30" as="geometry"/>
        </mxCell>
        <mxCell id="1SbDq5obIm_g6BfvqbwU-49" style="edgeStyle=orthogonalEdgeStyle;rounded=0;html=1;exitX=0.5;exitY=1;entryX=0;entryY=0.5;jettySize=auto;orthogonalLoop=1;" parent="1" source="1SbDq5obIm_g6BfvqbwU-23" target="1SbDq5obIm_g6BfvqbwU-48" edge="1">
          <mxGeometry relative="1" as="geometry"/>
        </mxCell>
        <mxCell id="1SbDq5obIm_g6BfvqbwU-53" style="edgeStyle=orthogonalEdgeStyle;rounded=0;html=1;exitX=0.5;exitY=1;entryX=0;entryY=0.5;jettySize=auto;orthogonalLoop=1;" parent="1" source="1SbDq5obIm_g6BfvqbwU-23" target="1SbDq5obIm_g6BfvqbwU-50" edge="1">
          <mxGeometry relative="1" as="geometry"/>
        </mxCell>
        <mxCell id="1SbDq5obIm_g6BfvqbwU-54" style="edgeStyle=orthogonalEdgeStyle;rounded=0;html=1;exitX=0.5;exitY=1;entryX=0;entryY=0.5;jettySize=auto;orthogonalLoop=1;" parent="1" source="1SbDq5obIm_g6BfvqbwU-23" target="1SbDq5obIm_g6BfvqbwU-51" edge="1">
          <mxGeometry relative="1" as="geometry"/>
        </mxCell>
        <mxCell id="1SbDq5obIm_g6BfvqbwU-55" style="edgeStyle=orthogonalEdgeStyle;rounded=0;html=1;exitX=0.5;exitY=1;entryX=0;entryY=0.5;jettySize=auto;orthogonalLoop=1;" parent="1" source="1SbDq5obIm_g6BfvqbwU-23" target="1SbDq5obIm_g6BfvqbwU-52" edge="1">
          <mxGeometry relative="1" as="geometry"/>
        </mxCell>
        <mxCell id="u9nL5F8PbuRC3VGXxQ7A-4" style="edgeStyle=orthogonalEdgeStyle;rounded=0;html=1;exitX=0.5;exitY=1;entryX=0;entryY=0.5;jettySize=auto;orthogonalLoop=1;" parent="1" source="1SbDq5obIm_g6BfvqbwU-23" target="u9nL5F8PbuRC3VGXxQ7A-3" edge="1">
          <mxGeometry relative="1" as="geometry"/>
        </mxCell>
        <mxCell id="1SbDq5obIm_g6BfvqbwU-23" value="Steel Pipes and C Channel" style="rounded=1;whiteSpace=wrap;html=1;fontSize=8;" parent="1" vertex="1">
          <mxGeometry x="-390.5" y="855.5" width="70" height="30" as="geometry"/>
        </mxCell>
        <mxCell id="1SbDq5obIm_g6BfvqbwU-32" style="edgeStyle=orthogonalEdgeStyle;rounded=0;html=1;exitX=0.5;exitY=1;entryX=0;entryY=0.5;jettySize=auto;orthogonalLoop=1;" parent="1" source="1SbDq5obIm_g6BfvqbwU-29" target="1SbDq5obIm_g6BfvqbwU-20" edge="1">
          <mxGeometry relative="1" as="geometry"/>
        </mxCell>
        <mxCell id="1SbDq5obIm_g6BfvqbwU-33" style="edgeStyle=orthogonalEdgeStyle;rounded=0;html=1;exitX=0.5;exitY=1;entryX=0;entryY=0.5;jettySize=auto;orthogonalLoop=1;" parent="1" source="1SbDq5obIm_g6BfvqbwU-29" target="1SbDq5obIm_g6BfvqbwU-21" edge="1">
          <mxGeometry relative="1" as="geometry"/>
        </mxCell>
        <mxCell id="1SbDq5obIm_g6BfvqbwU-34" style="edgeStyle=orthogonalEdgeStyle;rounded=0;html=1;exitX=0.5;exitY=1;entryX=0;entryY=0.5;jettySize=auto;orthogonalLoop=1;" parent="1" source="1SbDq5obIm_g6BfvqbwU-29" target="1SbDq5obIm_g6BfvqbwU-23" edge="1">
          <mxGeometry relative="1" as="geometry"/>
        </mxCell>
        <mxCell id="1SbDq5obIm_g6BfvqbwU-29" value="Subsidiary Companies’ Products " style="rounded=1;whiteSpace=wrap;html=1;" parent="1" vertex="1">
          <mxGeometry x="-480" y="395.5" width="120" height="60" as="geometry"/>
        </mxCell>
        <mxCell id="1SbDq5obIm_g6BfvqbwU-48" value="Round Pipe" style="rounded=1;whiteSpace=wrap;html=1;fontSize=8;" parent="1" vertex="1">
          <mxGeometry x="-318.5" y="895.5" width="70" height="30" as="geometry"/>
        </mxCell>
        <mxCell id="1SbDq5obIm_g6BfvqbwU-50" value="Square Pipe" style="rounded=1;whiteSpace=wrap;html=1;fontSize=8;" parent="1" vertex="1">
          <mxGeometry x="-318.5" y="935.5" width="70" height="30" as="geometry"/>
        </mxCell>
        <mxCell id="1SbDq5obIm_g6BfvqbwU-51" value="C Channel" style="rounded=1;whiteSpace=wrap;html=1;fontSize=8;" parent="1" vertex="1">
          <mxGeometry x="-318.5" y="975.5" width="70" height="30" as="geometry"/>
        </mxCell>
        <mxCell id="1SbDq5obIm_g6BfvqbwU-52" value="Galvanized Round Pipe" style="rounded=1;whiteSpace=wrap;html=1;fontSize=8;" parent="1" vertex="1">
          <mxGeometry x="-318.5" y="1015.5" width="70" height="30" as="geometry"/>
        </mxCell>
        <mxCell id="u9nL5F8PbuRC3VGXxQ7A-3" value="Electrical Wire Pipe" style="rounded=1;whiteSpace=wrap;html=1;fontSize=8;" parent="1" vertex="1">
          <mxGeometry x="-318.5" y="1055.5" width="70" height="30" as="geometry"/>
        </mxCell>
        <mxCell id="Dp0uku5MoqhAA5mbejGY-3" value="Our Capabilities" style="rounded=1;whiteSpace=wrap;html=1;fontSize=8;" parent="1" vertex="1">
          <mxGeometry x="72" y="450.5" width="70" height="30" as="geometry"/>
        </mxCell>
        <mxCell id="Dp0uku5MoqhAA5mbejGY-6" value="Executive Team" style="rounded=1;whiteSpace=wrap;html=1;fontSize=8;" parent="1" vertex="1">
          <mxGeometry x="-115" y="531" width="70" height="30" as="geometry"/>
        </mxCell>
        <mxCell id="Dp0uku5MoqhAA5mbejGY-10" value="Corporate Social and Environmental Responsibility" style="rounded=1;whiteSpace=wrap;html=1;fontSize=8;" parent="1" vertex="1">
          <mxGeometry x="72" y="491" width="70" height="40" as="geometry"/>
        </mxCell>
      </root>
    </mxGraphModel>
  </diagram>
</mxfile>
